{
  "@context": "http://iiif.io/api/presentation/2/context.json",
  "@id": "https://example.com/iiif/篳篥_双調_入破_1590-1592.json",
  "@type": "sc:Manifest",
  "label": "篳篥 双調 入破",
  "metadata": [
    {
      "label": "Title",
      "value": "入破"
    },
    {
      "label": "Instrument",
      "value": "篳篥"
    },
    {
      "label": "Cho-shi",
      "value": "双調"
    },
    {
      "label": "Size",
      "value": "大曲"
    },
    {
      "label": "Hyoshi",
      "value": "早六拍子"
    },
    {
      "label": "Cycle",
      "value": "拍子十六"
    },
    {
      "label": "Kuwae-hyoshi",
      "value": "半帖以下拍子加"
    },
    {
      "label": "Compilation Year",
      "value": "明治9年撰定"
    },
    {
      "label": "Page Range",
      "value": "1590-1592"
    },
    {
      "label": "DOI",
      "value": "10.20730/100270332"
    }
  ],
  "sequences": [
    {
      "@type": "sc:Sequence",
      "canvases": [
        {
          "@id": "https://kokusho.nijl.ac.jp/biblio/100270332/canvas/1590",
          "@type": "sc:Canvas",
          "label": "1590",
          "height": 4616,
          "width": 6088,
          "images": [
            {
              "@id": "https://kokusho.nijl.ac.jp/biblio/100270332/annotation/1590",
              "@type": "oa:Annotation",
              "motivation": "sc:painting",
              "resource": {
                "@id": "https://kokusho.nijl.ac.jp/api/iiif/100270332/v4/KSRM/KSRM-560302/KSRM-560302-1589.tif/full/full/0/default.jpg",
                "@type": "dctypes:Image",
                "format": "image/jpeg",
                "height": 4616,
                "width": 6088,
                "dc:identifier": "KSRM-560302",
                "service": {
                  "@context": "http://iiif.io/api/image/2/context.json",
                  "@id": "https://kokusho.nijl.ac.jp/api/iiif/100270332/v4/KSRM/KSRM-560302/KSRM-560302-1589.tif",
                  "profile": "http://iiif.io/api/image/2/level1.json"
                }
              },
              "on": "https://kokusho.nijl.ac.jp/biblio/100270332/canvas/1590"
            }
          ],
          "rendering": [
            {
              "id": "https://kokusho.nijl.ac.jp/api/iiif/100270332/v4/KSRM/KSRM-560302/KSRM-560302-1589.tif/full/full/0/default.jpg",
              "label": "Original (6088 x 4616px)",
              "format": "image/jpeg"
            }
          ]
        },
        {
          "@id": "https://kokusho.nijl.ac.jp/biblio/100270332/canvas/1591",
          "@type": "sc:Canvas",
          "label": "1591",
          "height": 4616,
          "width": 6088,
          "images": [
            {
              "@id": "https://kokusho.nijl.ac.jp/biblio/100270332/annotation/1591",
              "@type": "oa:Annotation",
              "motivation": "sc:painting",
              "resource": {
                "@id": "https://kokusho.nijl.ac.jp/api/iiif/100270332/v4/KSRM/KSRM-560302/KSRM-560302-1590.tif/full/full/0/default.jpg",
                "@type": "dctypes:Image",
                "format": "image/jpeg",
                "height": 4616,
                "width": 6088,
                "dc:identifier": "KSRM-560302",
                "service": {
                  "@context": "http://iiif.io/api/image/2/context.json",
                  "@id": "https://kokusho.nijl.ac.jp/api/iiif/100270332/v4/KSRM/KSRM-560302/KSRM-560302-1590.tif",
                  "profile": "http://iiif.io/api/image/2/level1.json"
                }
              },
              "on": "https://kokusho.nijl.ac.jp/biblio/100270332/canvas/1591"
            }
          ],
          "rendering": [
            {
              "id": "https://kokusho.nijl.ac.jp/api/iiif/100270332/v4/KSRM/KSRM-560302/KSRM-560302-1590.tif/full/full/0/default.jpg",
              "label": "Original (6088 x 4616px)",
              "format": "image/jpeg"
            }
          ]
        },
        {
          "@id": "https://kokusho.nijl.ac.jp/biblio/100270332/canvas/1592",
          "@type": "sc:Canvas",
          "label": "1592",
          "height": 4616,
          "width": 6088,
          "images": [
            {
              "@id": "https://kokusho.nijl.ac.jp/biblio/100270332/annotation/1592",
              "@type": "oa:Annotation",
              "motivation": "sc:painting",
              "resource": {
                "@id": "https://kokusho.nijl.ac.jp/api/iiif/100270332/v4/KSRM/KSRM-560302/KSRM-560302-1591.tif/full/full/0/default.jpg",
                "@type": "dctypes:Image",
                "format": "image/jpeg",
                "height": 4616,
                "width": 6088,
                "dc:identifier": "KSRM-560302",
                "service": {
                  "@context": "http://iiif.io/api/image/2/context.json",
                  "@id": "https://kokusho.nijl.ac.jp/api/iiif/100270332/v4/KSRM/KSRM-560302/KSRM-560302-1591.tif",
                  "profile": "http://iiif.io/api/image/2/level1.json"
                }
              },
              "on": "https://kokusho.nijl.ac.jp/biblio/100270332/canvas/1592"
            }
          ],
          "rendering": [
            {
              "id": "https://kokusho.nijl.ac.jp/api/iiif/100270332/v4/KSRM/KSRM-560302/KSRM-560302-1591.tif/full/full/0/default.jpg",
              "label": "Original (6088 x 4616px)",
              "format": "image/jpeg"
            }
          ]
        }
      ]
    }
  ]
}