{
  "@context": "http://iiif.io/api/presentation/2/context.json",
  "@id": "https://kokusho.nijl.ac.jp/biblio/100376839/manifest/3e64a9c7-4509-47c4-b535-5d7974cbe375",
  "@type": "sc:Manifest",
  "metadata": [
    {
      "label": "Title",
      "value": "武徳楽"
    },
    {
      "label": "Instrument",
      "value": "篳篥"
    },
    {
      "label": "Cho-shi",
      "value": "壱越調"
    },
    {
      "label": "Size",
      "value": "小曲"
    },
    {
      "label": "Hyoshi",
      "value": "早四拍子"
    },
    {
      "label": "Cycle",
      "value": "拍子十二"
    },
    {
      "label": "Compilation Year",
      "value": "明治21年撰定"
    },
    {
      "label": "Page Range",
      "value": "376-376"
    },
    {
      "label": "DOI",
      "value": "10.20730/100376839"
    }
  ],
  "label": "篳篥 壱越調 武徳楽",
  "attribution": "東京藝術大学附属図書館 国文学研究資料館",
  "license": "https://kokusho.nijl.ac.jp/page/usage.html",
  "viewingDirection": "right-to-left",
  "viewingHint": "individuals",
  "sequences": [
    {
      "@id": "https://kokusho.nijl.ac.jp/biblio/100376839/manifest/3e64a9c7-4509-47c4-b535-5d7974cbe375/sequence/normal",
      "@type": "sc:Sequence",
      "canvases": [
        {
          "@id": "https://kokusho.nijl.ac.jp/biblio/100376839/manifest/3e64a9c7-4509-47c4-b535-5d7974cbe375/canvas/1",
          "@type": "sc:Canvas",
          "label": "376",
          "height": 5668,
          "width": 8064,
          "images": [
            {
              "@id": "https://kokusho.nijl.ac.jp/biblio/100376839/manifest/3e64a9c7-4509-47c4-b535-5d7974cbe375/annotation/1",
              "@type": "oa:Annotation",
              "motivation": "sc:painting",
              "resource": {
                "@id": "https://kokusho.nijl.ac.jp/api/iiif/100376839/v4/TKGL/TKGL-20424/TKGL-20424-00375.tif/full/full/0/default.jpg",
                "@type": "dctypes:Image",
                "format": "image/jpeg",
                "height": 5668,
                "width": 8064,
                "dc:identifier": "TKGL-20424",
                "service": {
                  "@context": "http://iiif.io/api/image/2/context.json",
                  "@id": "https://kokusho.nijl.ac.jp/api/iiif/100376839/v4/TKGL/TKGL-20424/TKGL-20424-00375.tif",
                  "profile": "http://iiif.io/api/image/2/level1.json"
                }
              },
              "on": "https://kokusho.nijl.ac.jp/biblio/100376839/manifest/3e64a9c7-4509-47c4-b535-5d7974cbe375/canvas/1"
            }
          ],
          "rendering": [
            {
              "id": "https://kokusho.nijl.ac.jp/api/iiif/100376839/v4/TKGL/TKGL-20424/TKGL-20424-00375.tif/full/full/0/default.jpg",
              "label": "Original (8064 x 5668px)",
              "format": "image/jpeg"
            }
          ]
        }
      ]
    }
  ],
  "thumbnail": {
    "@id": "https://kokusho.nijl.ac.jp/api/iiif/100376839/v4/TKGL/TKGL-20424/TKGL-20424-00375.tif/full/200,/0/default.jpg",
    "@type": "dctypes:Image",
    "format": "image/jpeg",
    "service": {
      "@context": "http://iiif.io/api/image/2/context.json",
      "@id": "https://kokusho.nijl.ac.jp/api/iiif/100376839/v4/TKGL/TKGL-20424/TKGL-20424-00375.tif",
      "profile": "http://iiif.io/api/image/2/level1.json"
    }
  }
}